[
{"num":0.000,"ele":609.0},
{"num":0.310,"ele":617.0},
{"num":0.591,"ele":630.7},
{"num":1.443,"ele":668.7},
{"num":2.060,"ele":708.6},
{"num":2.535,"ele":740.0},
{"num":2.956,"ele":767.4},
{"num":3.310,"ele":789.4},
{"num":3.576,"ele":810.3},
{"num":3.871,"ele":832.3},
{"num":4.203,"ele":855.0},
{"num":4.422,"ele":872.9},
{"num":4.668,"ele":893.3},
{"num":4.973,"ele":916.1},
{"num":5.257,"ele":935.1},
{"num":5.515,"ele":952.0},
{"num":5.846,"ele":976.4},
{"num":6.086,"ele":998.1},
{"num":6.372,"ele":1017.7},
{"num":6.594,"ele":1036.6},
{"num":6.962,"ele":1065.9},
{"num":7.281,"ele":1083.0},
{"num":7.480,"ele":1101.9},
{"num":7.982,"ele":1127.1},
{"num":8.398,"ele":1163.6},
{"num":8.755,"ele":1195.1},
{"num":9.011,"ele":1219.3},
{"num":9.525,"ele":1241.0},
{"num":9.994,"ele":1242.9},
{"num":10.336,"ele":1255.6},
{"num":10.908,"ele":1294.3},
{"num":11.486,"ele":1334.0},
{"num":11.900,"ele":1348.3},
{"num":12.165,"ele":1367.6},
{"num":12.526,"ele":1403.7},
{"num":13.250,"ele":1457.9},
{"num":13.722,"ele":1496.4},
{"num":14.027,"ele":1515.3},
{"num":14.297,"ele":1522.3},
{"num":14.754,"ele":1500.3},
{"num":15.074,"ele":1477.1},
{"num":15.633,"ele":1447.3},
{"num":15.954,"ele":1423.7},
{"num":16.272,"ele":1403.0},
{"num":16.584,"ele":1380.3},
{"num":17.140,"ele":1344.6},
{"num":17.551,"ele":1321.0},
{"num":18.013,"ele":1292.3},
{"num":18.314,"ele":1266.9},
{"num":18.681,"ele":1255.7},
{"num":19.127,"ele":1234.3},
{"num":19.511,"ele":1208.4},
{"num":19.938,"ele":1199.1},
{"num":20.225,"ele":1202.7},
{"num":20.597,"ele":1201.6},
{"num":21.191,"ele":1161.3},
{"num":21.587,"ele":1131.7},
{"num":22.051,"ele":1111.3},
{"num":22.384,"ele":1099.1},
{"num":22.599,"ele":1077.6},
{"num":22.857,"ele":1057.1},
{"num":23.170,"ele":1035.1},
{"num":23.623,"ele":1001.4},
{"num":24.061,"ele":968.0},
{"num":24.454,"ele":941.4},
{"num":25.020,"ele":915.4},
{"num":25.370,"ele":890.7},
{"num":25.553,"ele":872.9},
{"num":25.730,"ele":860.6},
{"num":26.106,"ele":847.6},
{"num":26.535,"ele":823.4},
{"num":27.183,"ele":775.6},
{"num":27.602,"ele":730.0},
{"num":27.980,"ele":701.6},
{"num":28.282,"ele":675.7},
{"num":28.595,"ele":650.1},
{"num":28.832,"ele":624.7},
{"num":29.118,"ele":607.1},
{"num":29.419,"ele":587.6},
{"num":29.671,"ele":573.1},
{"num":30.039,"ele":546.0},
{"num":30.300,"ele":527.0},
{"num":30.506,"ele":508.3},
{"num":30.711,"ele":500.9},
{"num":31.078,"ele":505.3},
{"num":31.540,"ele":510.3},
{"num":31.799,"ele":516.6},
{"num":31.975,"ele":512.0},
{"num":32.174,"ele":515.1},
{"num":32.382,"ele":513.4},
{"num":32.604,"ele":523.1},
{"num":32.825,"ele":538.3},
{"num":32.856,"ele":538.3},
{"num":33.075,"ele":533.9},
{"num":33.300,"ele":600.9},
{"num":33.549,"ele":605.9},
{"num":33.747,"ele":610.9},
{"num":33.958,"ele":615.9},
{"num":34.152,"ele":620.9},
{"num":34.260,"ele":625.9},
{"num":34.406,"ele":628.9},
{"num":34.544,"ele":630.3},
{"num":34.700,"ele":643.0},
{"num":34.914,"ele":679.4},
{"num":35.113,"ele":700.0},
{"num":35.320,"ele":710.0},
{"num":35.459,"ele":733.1},
{"num":35.627,"ele":751.7},
{"num":35.752,"ele":758.0},
{"num":35.888,"ele":756.3},
{"num":36.052,"ele":762.3},
{"num":36.233,"ele":783.3},
{"num":36.354,"ele":791.3},
{"num":36.487,"ele":785.3},
{"num":36.659,"ele":777.6},
{"num":36.844,"ele":764.9},
{"num":36.983,"ele":748.9},
{"num":37.139,"ele":722.0},
{"num":37.269,"ele":708.6},
{"num":37.403,"ele":702.4},
{"num":37.507,"ele":687.1},
{"num":37.588,"ele":670.6},
{"num":37.683,"ele":652.0},
{"num":37.815,"ele":633.0},
{"num":37.964,"ele":608.7},
{"num":38.121,"ele":578.3},
{"num":38.305,"ele":569.3},
{"num":38.509,"ele":592.0},
{"num":38.722,"ele":612.7},
{"num":38.951,"ele":644.0},
{"num":39.207,"ele":662.1},
{"num":39.388,"ele":638.3},
{"num":39.571,"ele":605.6},
{"num":39.766,"ele":641.9},
{"num":39.975,"ele":670.7},
{"num":40.207,"ele":672.3},
{"num":40.441,"ele":676.0},
{"num":40.694,"ele":676.9},
{"num":40.954,"ele":687.7},
{"num":41.225,"ele":689.3},
{"num":41.578,"ele":680.9},
{"num":41.821,"ele":679.1},
{"num":42.141,"ele":681.7},
{"num":42.500,"ele":684.9},
{"num":42.859,"ele":682.1},
{"num":43.249,"ele":680.3},
{"num":43.249,"ele":680.3},
{"num":43.562,"ele":676.7},
{"num":43.873,"ele":668.3},
{"num":44.103,"ele":655.4},
{"num":44.562,"ele":625.4},
{"num":44.780,"ele":620.1},
{"num":45.036,"ele":617.9},
{"num":45.447,"ele":609.6},
{"num":45.909,"ele":615.3},
{"num":46.361,"ele":632.3},
{"num":46.940,"ele":652.9},
{"num":47.821,"ele":658.3},
{"num":48.492,"ele":654.1},
{"num":48.905,"ele":646.6},
{"num":49.692,"ele":625.7},
{"num":50.330,"ele":614.7}
]