[
{"num":0.000,"ele":370.7},
{"num":0.176,"ele":373.5},
{"num":0.278,"ele":381.8},
{"num":0.376,"ele":391.3},
{"num":0.481,"ele":399.1},
{"num":0.592,"ele":406.3},
{"num":0.698,"ele":416.2},
{"num":0.813,"ele":427.0},
{"num":0.918,"ele":431.5},
{"num":1.122,"ele":417.8},
{"num":1.525,"ele":398.7},
{"num":1.661,"ele":393.9},
{"num":1.841,"ele":388.0},
{"num":1.990,"ele":380.4},
{"num":2.133,"ele":378.5},
{"num":2.274,"ele":376.4},
{"num":2.385,"ele":372.5},
{"num":2.541,"ele":367.2},
{"num":2.720,"ele":355.3},
{"num":2.870,"ele":340.4},
{"num":2.991,"ele":326.5},
{"num":3.169,"ele":308.0},
{"num":3.311,"ele":292.4},
{"num":3.472,"ele":277.1},
{"num":3.586,"ele":268.0},
{"num":3.702,"ele":254.5},
{"num":3.926,"ele":235.9},
{"num":4.063,"ele":225.9},
{"num":4.274,"ele":217.8},
{"num":4.387,"ele":216.0},
{"num":4.531,"ele":221.3},
{"num":4.647,"ele":220.7},
{"num":4.821,"ele":207.6},
{"num":5.042,"ele":193.6},
{"num":5.194,"ele":184.5},
{"num":5.366,"ele":175.4},
{"num":5.543,"ele":169.9},
{"num":5.739,"ele":165.0},
{"num":5.977,"ele":158.0},
{"num":6.103,"ele":154.1},
{"num":6.300,"ele":149.6},
{"num":6.467,"ele":155.0},
{"num":6.577,"ele":160.3},
{"num":6.771,"ele":154.7},
{"num":6.997,"ele":142.7},
{"num":7.217,"ele":140.7},
{"num":7.383,"ele":138.5},
{"num":7.544,"ele":128.9},
{"num":7.676,"ele":121.6},
{"num":7.814,"ele":119.6},
{"num":7.964,"ele":117.9},
{"num":8.163,"ele":114.2},
{"num":8.478,"ele":109.2},
{"num":8.737,"ele":106.7},
{"num":8.839,"ele":107.5},
{"num":9.058,"ele":104.4},
{"num":9.421,"ele":103.2},
{"num":9.601,"ele":104.9},
{"num":9.784,"ele":108.9},
{"num":9.947,"ele":115.0},
{"num":10.196,"ele":124.2},
{"num":10.372,"ele":130.2},
{"num":10.559,"ele":128.1},
{"num":10.734,"ele":120.9},
{"num":10.910,"ele":125.1},
{"num":11.043,"ele":131.6},
{"num":11.214,"ele":135.0},
{"num":11.511,"ele":139.4},
{"num":11.823,"ele":142.7},
{"num":12.028,"ele":143.0},
{"num":12.204,"ele":139.5},
{"num":12.418,"ele":139.3},
{"num":12.607,"ele":148.4},
{"num":12.802,"ele":157.8},
{"num":12.910,"ele":163.5},
{"num":13.069,"ele":166.0},
{"num":13.284,"ele":165.3},
{"num":13.544,"ele":166.9},
{"num":13.714,"ele":170.5},
{"num":13.846,"ele":169.4},
{"num":14.013,"ele":173.7},
{"num":14.135,"ele":174.1},
{"num":14.327,"ele":168.2},
{"num":14.582,"ele":170.5},
{"num":14.784,"ele":179.0},
{"num":14.957,"ele":185.3},
{"num":15.099,"ele":196.3},
{"num":15.229,"ele":204.5},
{"num":15.390,"ele":211.7},
{"num":15.544,"ele":219.0},
{"num":15.805,"ele":222.0},
{"num":15.981,"ele":228.3},
{"num":16.089,"ele":236.5},
{"num":16.226,"ele":244.1},
{"num":16.322,"ele":256.9},
{"num":16.417,"ele":270.8},
{"num":16.544,"ele":273.2},
{"num":16.679,"ele":265.9},
{"num":16.908,"ele":256.6},
{"num":17.067,"ele":246.3},
{"num":17.191,"ele":235.8},
{"num":17.455,"ele":229.2},
{"num":17.632,"ele":235.7},
{"num":17.761,"ele":240.1},
{"num":17.892,"ele":227.2},
{"num":18.114,"ele":205.7},
{"num":18.319,"ele":197.1},
{"num":18.499,"ele":193.5},
{"num":18.673,"ele":186.7},
{"num":18.807,"ele":177.1},
{"num":18.974,"ele":169.8},
{"num":19.190,"ele":160.6},
{"num":19.334,"ele":153.3},
{"num":19.514,"ele":145.2},
{"num":19.662,"ele":140.6},
{"num":19.886,"ele":135.7},
{"num":20.156,"ele":135.2},
{"num":20.451,"ele":138.2},
{"num":20.705,"ele":144.0},
{"num":20.869,"ele":149.6},
{"num":21.058,"ele":150.1},
{"num":21.165,"ele":150.0},
{"num":21.351,"ele":153.2},
{"num":21.502,"ele":161.2},
{"num":21.694,"ele":169.1},
{"num":21.899,"ele":174.6},
{"num":22.127,"ele":171.0},
{"num":22.270,"ele":164.7},
{"num":22.465,"ele":166.4},
{"num":22.609,"ele":167.5},
{"num":22.733,"ele":169.0},
{"num":22.927,"ele":172.6},
{"num":23.132,"ele":176.4},
{"num":23.313,"ele":178.9},
{"num":23.522,"ele":182.3},
{"num":23.644,"ele":189.8},
{"num":23.786,"ele":190.6},
{"num":23.927,"ele":191.6},
{"num":24.072,"ele":195.9},
{"num":24.175,"ele":207.2},
{"num":24.304,"ele":216.5},
{"num":24.424,"ele":215.4},
{"num":24.647,"ele":206.4},
{"num":24.800,"ele":206.6},
{"num":24.977,"ele":209.8},
{"num":25.122,"ele":218.6},
{"num":25.209,"ele":229.9},
{"num":25.307,"ele":238.8},
{"num":25.502,"ele":238.8},
{"num":25.717,"ele":239.5},
{"num":25.905,"ele":244.2},
{"num":26.068,"ele":249.2},
{"num":26.279,"ele":252.8},
{"num":26.455,"ele":256.6},
{"num":26.602,"ele":260.9},
{"num":26.778,"ele":263.2},
{"num":26.917,"ele":264.1},
{"num":27.039,"ele":264.3},
{"num":27.250,"ele":263.5},
{"num":27.415,"ele":262.1},
{"num":27.588,"ele":257.8},
{"num":27.815,"ele":263.7},
{"num":27.989,"ele":265.4},
{"num":28.146,"ele":271.1},
{"num":28.248,"ele":282.0},
{"num":28.358,"ele":289.4},
{"num":28.539,"ele":295.1},
{"num":28.766,"ele":288.7},
{"num":29.034,"ele":288.5},
{"num":29.248,"ele":292.8},
{"num":29.439,"ele":299.0},
{"num":29.649,"ele":305.1},
{"num":29.851,"ele":311.4},
{"num":30.033,"ele":317.9},
{"num":30.290,"ele":325.5},
{"num":30.499,"ele":333.2},
{"num":30.741,"ele":342.5},
{"num":30.905,"ele":349.7},
{"num":31.136,"ele":355.7},
{"num":31.307,"ele":357.8},
{"num":31.595,"ele":354.1},
{"num":31.814,"ele":350.8},
{"num":31.980,"ele":352.5},
{"num":32.177,"ele":346.8},
{"num":32.409,"ele":344.1},
{"num":32.574,"ele":348.4},
{"num":32.696,"ele":354.1},
{"num":32.869,"ele":356.8},
{"num":32.997,"ele":347.9},
{"num":33.162,"ele":340.2},
{"num":33.265,"ele":342.4},
{"num":33.377,"ele":344.1},
{"num":33.538,"ele":346.9},
{"num":33.671,"ele":352.1},
{"num":33.835,"ele":349.0},
{"num":33.970,"ele":345.7},
{"num":34.089,"ele":341.3},
{"num":34.288,"ele":333.9},
{"num":34.431,"ele":331.3},
{"num":34.560,"ele":330.3},
{"num":34.717,"ele":327.3},
{"num":34.833,"ele":324.7},
{"num":34.952,"ele":324.3},
{"num":35.106,"ele":321.0},
{"num":35.262,"ele":315.4},
{"num":35.412,"ele":310.0},
{"num":35.566,"ele":305.5},
{"num":35.739,"ele":292.6},
{"num":35.837,"ele":280.7},
{"num":35.979,"ele":260.5},
{"num":36.103,"ele":241.3},
{"num":36.279,"ele":228.6},
{"num":36.390,"ele":224.6},
{"num":36.547,"ele":219.6},
{"num":36.684,"ele":216.0},
{"num":36.843,"ele":210.7},
{"num":37.065,"ele":204.9},
{"num":37.243,"ele":200.7},
{"num":37.446,"ele":201.4},
{"num":37.649,"ele":203.0},
{"num":37.831,"ele":205.4},
{"num":38.024,"ele":207.8},
{"num":38.251,"ele":209.7},
{"num":38.438,"ele":209.3},
{"num":38.548,"ele":209.4},
{"num":38.691,"ele":213.5},
{"num":38.891,"ele":219.3},
{"num":39.013,"ele":228.6},
{"num":39.140,"ele":240.3},
{"num":39.249,"ele":253.0},
{"num":39.379,"ele":261.1},
{"num":39.491,"ele":269.3},
{"num":39.671,"ele":282.6},
{"num":39.794,"ele":288.7},
{"num":39.947,"ele":291.5},
{"num":40.110,"ele":294.5},
{"num":40.267,"ele":297.1},
{"num":40.398,"ele":299.3},
{"num":40.585,"ele":301.8},
{"num":40.735,"ele":305.1},
{"num":40.934,"ele":310.0},
{"num":41.109,"ele":317.2},
{"num":41.283,"ele":325.6},
{"num":41.425,"ele":331.8},
{"num":41.596,"ele":336.1},
{"num":41.768,"ele":339.1},
{"num":41.894,"ele":343.0},
{"num":42.044,"ele":345.8},
{"num":42.170,"ele":345.2},
{"num":42.303,"ele":351.6},
{"num":42.416,"ele":355.1},
{"num":42.587,"ele":361.7},
{"num":42.772,"ele":367.6},
{"num":42.901,"ele":375.0},
{"num":43.029,"ele":382.3},
{"num":43.157,"ele":391.1},
{"num":43.289,"ele":400.4},
{"num":43.407,"ele":410.9},
{"num":43.528,"ele":421.6},
{"num":43.651,"ele":437.9},
{"num":43.770,"ele":438.5},
{"num":43.885,"ele":445.3},
{"num":44.006,"ele":452.7},
{"num":44.110,"ele":459.3},
{"num":44.198,"ele":465.3},
{"num":44.307,"ele":474.2},
{"num":44.435,"ele":482.7},
{"num":44.554,"ele":491.0},
{"num":44.666,"ele":500.3},
{"num":44.763,"ele":506.9},
{"num":44.872,"ele":514.3},
{"num":44.965,"ele":523.0},
{"num":45.066,"ele":531.7},
{"num":45.154,"ele":539.7},
{"num":45.244,"ele":552.5},
{"num":45.362,"ele":564.6},
{"num":45.522,"ele":570.9},
{"num":45.630,"ele":575.2},
{"num":45.809,"ele":575.9},
{"num":45.928,"ele":589.8},
{"num":46.042,"ele":602.1},
{"num":46.151,"ele":608.5},
{"num":46.300,"ele":609.1},
{"num":46.424,"ele":606.9},
{"num":46.599,"ele":603.0},
{"num":46.741,"ele":605.8},
{"num":46.950,"ele":604.2},
{"num":47.150,"ele":594.9},
{"num":47.338,"ele":593.4},
{"num":47.476,"ele":594.8},
{"num":47.631,"ele":598.5},
{"num":47.784,"ele":604.5},
{"num":47.951,"ele":611.0},
{"num":48.105,"ele":613.3},
{"num":51.029,"ele":634.6},
{"num":52.681,"ele":552.1},
{"num":53.814,"ele":416.1},
{"num":54.916,"ele":374.0}
]