[
{"num":0.000,"ele":471.3},
{"num":0.067,"ele":474.6},
{"num":0.139,"ele":478.7},
{"num":0.221,"ele":481.8},
{"num":0.310,"ele":479.4},
{"num":0.485,"ele":469.3},
{"num":0.594,"ele":470.1},
{"num":0.666,"ele":475.2},
{"num":0.684,"ele":478.5},
{"num":0.729,"ele":483.0},
{"num":0.773,"ele":487.2},
{"num":0.812,"ele":491.6},
{"num":0.856,"ele":494.9},
{"num":0.891,"ele":499.1},
{"num":0.912,"ele":501.7},
{"num":0.931,"ele":505.9},
{"num":0.951,"ele":509.6},
{"num":0.971,"ele":512.0},
{"num":0.994,"ele":514.8},
{"num":1.014,"ele":517.4},
{"num":1.034,"ele":520.7},
{"num":1.057,"ele":525.2},
{"num":1.064,"ele":526.7},
{"num":1.064,"ele":526.8},
{"num":1.064,"ele":526.8},
{"num":1.064,"ele":526.8},
{"num":1.064,"ele":526.8},
{"num":1.064,"ele":526.8},
{"num":1.064,"ele":526.8},
{"num":1.064,"ele":526.8},
{"num":1.064,"ele":526.8},
{"num":1.064,"ele":526.8},
{"num":1.064,"ele":526.8},
{"num":1.064,"ele":526.8},
{"num":1.064,"ele":526.8},
{"num":1.068,"ele":527.4},
{"num":1.074,"ele":528.0},
{"num":1.074,"ele":528.0},
{"num":1.074,"ele":528.0},
{"num":1.074,"ele":528.0},
{"num":1.074,"ele":528.0},
{"num":1.074,"ele":528.0},
{"num":1.074,"ele":528.2},
{"num":1.127,"ele":525.8},
{"num":1.223,"ele":525.5},
{"num":1.300,"ele":523.2},
{"num":1.453,"ele":517.6},
{"num":1.621,"ele":510.8},
{"num":1.790,"ele":504.7},
{"num":1.949,"ele":496.9},
{"num":2.135,"ele":489.3},
{"num":2.320,"ele":483.3},
{"num":2.485,"ele":474.6},
{"num":2.553,"ele":470.6},
{"num":2.585,"ele":470.2},
{"num":2.592,"ele":470.1},
{"num":2.592,"ele":470.1},
{"num":2.592,"ele":470.1},
{"num":2.592,"ele":470.1},
{"num":2.592,"ele":470.1},
{"num":2.592,"ele":470.1},
{"num":2.592,"ele":470.1},
{"num":2.592,"ele":470.1},
{"num":2.592,"ele":470.1},
{"num":2.592,"ele":470.1},
{"num":2.592,"ele":470.1},
{"num":2.592,"ele":470.1},
{"num":2.592,"ele":470.1},
{"num":2.592,"ele":470.4},
{"num":2.634,"ele":472.9},
{"num":2.691,"ele":476.2},
{"num":2.765,"ele":480.4},
{"num":2.853,"ele":483.3},
{"num":2.943,"ele":485.9},
{"num":3.028,"ele":488.9},
{"num":3.112,"ele":492.5},
{"num":3.195,"ele":495.4},
{"num":3.275,"ele":498.7},
{"num":3.356,"ele":502.2},
{"num":3.441,"ele":507.1},
{"num":3.525,"ele":509.9},
{"num":3.611,"ele":511.7},
{"num":3.698,"ele":516.2},
{"num":3.782,"ele":519.5},
{"num":3.872,"ele":521.7},
{"num":3.947,"ele":524.2},
{"num":4.021,"ele":525.1},
{"num":4.132,"ele":527.8},
{"num":4.192,"ele":535.3},
{"num":4.249,"ele":539.9},
{"num":4.300,"ele":543.9},
{"num":4.354,"ele":549.5},
{"num":4.406,"ele":553.9},
{"num":4.466,"ele":557.2},
{"num":4.562,"ele":556.0},
{"num":4.681,"ele":554.7},
{"num":4.768,"ele":552.8},
{"num":4.808,"ele":550.4},
{"num":4.832,"ele":551.7},
{"num":4.832,"ele":551.8},
{"num":4.832,"ele":551.8},
{"num":4.832,"ele":551.8},
{"num":4.832,"ele":552.3},
{"num":4.898,"ele":550.6},
{"num":5.024,"ele":545.6},
{"num":5.183,"ele":537.3},
{"num":5.351,"ele":529.5},
{"num":5.479,"ele":521.5},
{"num":5.607,"ele":511.0},
{"num":5.719,"ele":499.6},
{"num":5.850,"ele":489.5},
{"num":5.971,"ele":478.4},
{"num":6.074,"ele":467.5},
{"num":6.141,"ele":456.3},
{"num":6.221,"ele":443.6},
{"num":6.289,"ele":437.2},
{"num":6.392,"ele":432.2},
{"num":6.465,"ele":427.2},
{"num":6.564,"ele":422.1},
{"num":6.670,"ele":416.2},
{"num":6.761,"ele":410.8},
{"num":6.828,"ele":404.2},
{"num":6.898,"ele":398.6},
{"num":6.991,"ele":395.9},
{"num":7.083,"ele":392.4},
{"num":7.136,"ele":386.8},
{"num":7.197,"ele":382.8},
{"num":7.259,"ele":379.6},
{"num":7.335,"ele":376.5},
{"num":7.440,"ele":375.0},
{"num":7.459,"ele":372.4},
{"num":7.521,"ele":370.0},
{"num":7.601,"ele":369.2},
{"num":7.699,"ele":368.7},
{"num":7.761,"ele":369.9},
{"num":7.761,"ele":370.2},
{"num":7.761,"ele":370.2},
{"num":7.761,"ele":370.2},
{"num":7.761,"ele":370.0},
{"num":7.844,"ele":369.0},
{"num":7.929,"ele":369.2},
{"num":7.968,"ele":371.8},
{"num":8.005,"ele":376.4},
{"num":8.049,"ele":379.4},
{"num":8.088,"ele":383.3},
{"num":8.155,"ele":385.3},
{"num":8.236,"ele":386.3},
{"num":8.304,"ele":388.8},
{"num":8.370,"ele":392.5},
{"num":8.414,"ele":396.8},
{"num":8.479,"ele":400.7},
{"num":8.549,"ele":406.1},
{"num":8.627,"ele":409.7},
{"num":8.708,"ele":411.8},
{"num":8.794,"ele":415.1},
{"num":8.873,"ele":419.6},
{"num":8.946,"ele":424.0},
{"num":9.002,"ele":428.6},
{"num":9.045,"ele":432.0},
{"num":9.107,"ele":434.5},
{"num":9.177,"ele":437.2},
{"num":9.251,"ele":440.1},
{"num":9.317,"ele":442.0},
{"num":9.407,"ele":442.1},
{"num":9.462,"ele":446.1},
{"num":9.536,"ele":449.0},
{"num":9.629,"ele":446.1},
{"num":9.731,"ele":444.7},
{"num":9.836,"ele":444.0},
{"num":9.906,"ele":445.1},
{"num":9.985,"ele":443.6},
{"num":10.082,"ele":435.2},
{"num":10.166,"ele":425.3},
{"num":10.229,"ele":416.9},
{"num":10.331,"ele":410.1},
{"num":10.427,"ele":403.4},
{"num":10.452,"ele":401.9},
{"num":10.484,"ele":404.2},
{"num":10.528,"ele":408.0},
{"num":10.569,"ele":411.9},
{"num":10.605,"ele":415.9},
{"num":10.646,"ele":420.5},
{"num":10.667,"ele":423.6},
{"num":10.688,"ele":426.7},
{"num":10.719,"ele":429.5},
{"num":10.757,"ele":432.8},
{"num":10.796,"ele":436.0},
{"num":10.848,"ele":438.5},
{"num":10.899,"ele":440.1},
{"num":10.979,"ele":442.2},
{"num":11.035,"ele":445.7},
{"num":11.093,"ele":447.7},
{"num":11.176,"ele":447.8},
{"num":11.292,"ele":446.0},
{"num":11.355,"ele":447.3},
{"num":11.400,"ele":450.7},
{"num":11.413,"ele":450.0},
{"num":11.433,"ele":447.6},
{"num":11.512,"ele":444.7},
{"num":11.582,"ele":447.3},
{"num":11.660,"ele":448.8},
{"num":11.773,"ele":445.6},
{"num":11.887,"ele":440.8},
{"num":11.964,"ele":440.4},
{"num":12.017,"ele":439.6},
{"num":12.055,"ele":439.9},
{"num":12.084,"ele":440.7},
{"num":12.084,"ele":440.7},
{"num":12.084,"ele":440.7},
{"num":12.084,"ele":440.7},
{"num":12.084,"ele":440.7},
{"num":12.084,"ele":440.7},
{"num":12.084,"ele":440.7},
{"num":12.084,"ele":440.7},
{"num":12.084,"ele":440.7},
{"num":12.084,"ele":440.7},
{"num":12.084,"ele":440.7},
{"num":12.084,"ele":440.7},
{"num":12.084,"ele":440.7},
{"num":12.084,"ele":440.7},
{"num":12.084,"ele":440.7},
{"num":12.084,"ele":440.7},
{"num":12.084,"ele":440.7},
{"num":12.084,"ele":440.7},
{"num":12.084,"ele":440.7},
{"num":12.084,"ele":440.7},
{"num":12.084,"ele":440.7},
{"num":12.084,"ele":440.7},
{"num":12.084,"ele":440.7},
{"num":12.084,"ele":440.7},
{"num":12.084,"ele":440.7},
{"num":12.084,"ele":440.7},
{"num":12.084,"ele":440.7},
{"num":12.084,"ele":440.7},
{"num":12.084,"ele":440.7},
{"num":12.084,"ele":440.7},
{"num":12.084,"ele":440.7},
{"num":12.084,"ele":440.7},
{"num":12.084,"ele":440.7},
{"num":12.084,"ele":440.7},
{"num":12.084,"ele":440.7},
{"num":12.084,"ele":440.7},
{"num":12.084,"ele":440.7},
{"num":12.084,"ele":440.7},
{"num":12.084,"ele":440.7},
{"num":12.084,"ele":440.7},
{"num":12.084,"ele":440.7},
{"num":12.084,"ele":440.7},
{"num":12.084,"ele":440.7},
{"num":12.099,"ele":440.6},
{"num":12.186,"ele":441.5},
{"num":12.243,"ele":444.7},
{"num":12.302,"ele":447.3},
{"num":12.387,"ele":448.0},
{"num":12.488,"ele":446.5},
{"num":12.577,"ele":446.5},
{"num":12.620,"ele":450.1},
{"num":12.639,"ele":452.8},
{"num":12.662,"ele":455.5},
{"num":12.684,"ele":458.8},
{"num":12.699,"ele":463.2},
{"num":12.730,"ele":466.2},
{"num":12.778,"ele":469.3},
{"num":12.845,"ele":472.9},
{"num":12.910,"ele":473.2},
{"num":13.022,"ele":466.3},
{"num":13.114,"ele":464.4},
{"num":13.190,"ele":457.5},
{"num":13.297,"ele":448.6},
{"num":13.387,"ele":440.4},
{"num":13.442,"ele":440.4},
{"num":13.489,"ele":443.6},
{"num":13.536,"ele":447.9},
{"num":13.577,"ele":452.2},
{"num":13.619,"ele":455.9},
{"num":13.659,"ele":459.7},
{"num":13.700,"ele":464.0},
{"num":13.746,"ele":468.4},
{"num":13.793,"ele":472.2},
{"num":13.832,"ele":477.8},
{"num":13.872,"ele":483.3},
{"num":13.912,"ele":489.4},
{"num":13.951,"ele":493.4},
{"num":14.006,"ele":493.2},
{"num":14.049,"ele":498.0},
{"num":14.098,"ele":503.9},
{"num":14.141,"ele":509.8},
{"num":14.186,"ele":514.3},
{"num":14.235,"ele":519.1},
{"num":14.278,"ele":523.5},
{"num":14.321,"ele":527.4},
{"num":14.377,"ele":530.2},
{"num":14.486,"ele":531.7},
{"num":14.630,"ele":529.2},
{"num":14.789,"ele":527.4},
{"num":14.947,"ele":525.2},
{"num":15.099,"ele":522.4},
{"num":15.218,"ele":523.9},
{"num":15.318,"ele":527.4},
{"num":15.429,"ele":528.4},
{"num":15.548,"ele":529.5},
{"num":15.678,"ele":529.4},
{"num":15.842,"ele":524.5},
{"num":16.030,"ele":516.7},
{"num":16.220,"ele":509.6},
{"num":16.407,"ele":502.1},
{"num":16.588,"ele":493.4},
{"num":16.777,"ele":486.4},
{"num":16.966,"ele":478.3},
{"num":17.107,"ele":470.7},
{"num":17.142,"ele":469.6},
{"num":17.142,"ele":469.6},
{"num":17.142,"ele":469.6},
{"num":17.142,"ele":469.6},
{"num":17.142,"ele":469.8},
{"num":17.172,"ele":472.1},
{"num":17.226,"ele":474.2},
{"num":17.332,"ele":473.3},
{"num":17.472,"ele":474.1},
{"num":17.593,"ele":474.1},
{"num":17.696,"ele":473.8},
{"num":17.775,"ele":477.9},
{"num":17.880,"ele":476.0},
{"num":18.065,"ele":467.0},
{"num":18.248,"ele":457.6},
{"num":18.365,"ele":451.1},
{"num":18.474,"ele":440.5},
{"num":18.562,"ele":433.1},
{"num":18.628,"ele":436.0},
{"num":18.680,"ele":439.5},
{"num":18.742,"ele":441.1},
{"num":18.820,"ele":437.8},
{"num":18.894,"ele":436.0},
{"num":19.019,"ele":431.3},
{"num":19.137,"ele":424.4},
{"num":19.241,"ele":422.5},
{"num":19.299,"ele":423.5},
{"num":19.338,"ele":424.2},
{"num":19.407,"ele":425.0},
{"num":19.503,"ele":422.5},
{"num":19.580,"ele":420.2},
{"num":19.631,"ele":426.7},
{"num":19.671,"ele":431.7},
{"num":19.747,"ele":432.1},
{"num":19.850,"ele":427.1},
{"num":19.932,"ele":423.7},
{"num":20.022,"ele":420.3},
{"num":20.139,"ele":419.4},
{"num":20.237,"ele":418.9},
{"num":20.329,"ele":423.4},
{"num":20.399,"ele":424.6},
{"num":20.438,"ele":421.8},
{"num":20.496,"ele":421.4},
{"num":20.543,"ele":426.8},
{"num":20.595,"ele":430.1},
{"num":20.650,"ele":430.2},
{"num":20.707,"ele":433.2},
{"num":20.735,"ele":436.9},
{"num":20.798,"ele":435.5},
{"num":20.864,"ele":430.5},
{"num":20.924,"ele":420.7},
{"num":20.983,"ele":409.0},
{"num":21.088,"ele":398.0},
{"num":21.196,"ele":388.4},
{"num":21.272,"ele":382.5},
{"num":21.328,"ele":380.1},
{"num":21.389,"ele":383.1},
{"num":21.444,"ele":386.5},
{"num":21.518,"ele":388.2},
{"num":21.584,"ele":389.7},
{"num":21.659,"ele":394.4},
{"num":21.721,"ele":397.6},
{"num":21.779,"ele":402.8},
{"num":21.834,"ele":407.0},
{"num":21.888,"ele":408.8},
{"num":21.958,"ele":410.9},
{"num":22.001,"ele":412.3},
{"num":22.021,"ele":412.9},
{"num":22.050,"ele":416.5},
{"num":22.090,"ele":421.7},
{"num":22.134,"ele":427.0},
{"num":22.179,"ele":431.2},
{"num":22.232,"ele":432.7},
{"num":22.314,"ele":432.5},
{"num":22.435,"ele":430.3},
{"num":22.538,"ele":431.8},
{"num":22.633,"ele":431.0},
{"num":22.674,"ele":430.9},
{"num":22.690,"ele":430.1},
{"num":22.723,"ele":430.1},
{"num":22.747,"ele":431.7},
{"num":22.805,"ele":431.3},
{"num":22.873,"ele":430.9},
{"num":22.911,"ele":431.1},
{"num":22.985,"ele":431.4},
{"num":23.068,"ele":431.0},
{"num":23.125,"ele":430.9},
{"num":23.153,"ele":432.2},
{"num":23.241,"ele":432.6},
{"num":23.334,"ele":433.3},
{"num":23.411,"ele":432.4},
{"num":23.511,"ele":432.2},
{"num":23.596,"ele":431.2},
{"num":23.695,"ele":429.5},
{"num":23.812,"ele":426.3},
{"num":23.921,"ele":423.8},
{"num":24.047,"ele":415.7},
{"num":24.139,"ele":409.7},
{"num":24.250,"ele":408.8},
{"num":24.327,"ele":407.5},
{"num":24.365,"ele":407.9},
{"num":24.394,"ele":409.3},
{"num":24.416,"ele":408.4},
{"num":24.444,"ele":407.9},
{"num":24.492,"ele":407.8},
{"num":24.510,"ele":408.6},
{"num":24.537,"ele":410.4},
{"num":24.571,"ele":413.4},
{"num":24.584,"ele":416.3},
{"num":24.616,"ele":421.2},
{"num":24.640,"ele":425.4},
{"num":24.661,"ele":428.4},
{"num":24.682,"ele":430.7},
{"num":24.731,"ele":432.2},
{"num":24.813,"ele":432.0},
{"num":24.890,"ele":433.0},
{"num":24.961,"ele":433.1},
{"num":25.057,"ele":433.2},
{"num":25.136,"ele":431.6},
{"num":25.188,"ele":431.0},
{"num":25.229,"ele":431.6},
{"num":25.316,"ele":431.2},
{"num":25.388,"ele":431.5},
{"num":25.462,"ele":432.3},
{"num":25.526,"ele":433.0},
{"num":25.599,"ele":432.7},
{"num":25.666,"ele":429.9},
{"num":25.725,"ele":423.3},
{"num":25.786,"ele":416.0},
{"num":25.831,"ele":412.3},
{"num":25.897,"ele":407.9},
{"num":25.978,"ele":404.1},
{"num":26.079,"ele":398.3},
{"num":26.166,"ele":394.6},
{"num":26.253,"ele":390.3},
{"num":26.327,"ele":388.8},
{"num":26.408,"ele":385.3},
{"num":26.494,"ele":380.6},
{"num":26.548,"ele":376.7},
{"num":26.674,"ele":369.4},
{"num":26.811,"ele":360.3},
{"num":26.923,"ele":350.0},
{"num":27.051,"ele":338.3},
{"num":27.202,"ele":328.9},
{"num":27.301,"ele":325.6},
{"num":27.427,"ele":320.5},
{"num":27.534,"ele":321.0},
{"num":27.637,"ele":324.0},
{"num":27.723,"ele":324.8},
{"num":27.805,"ele":324.8},
{"num":27.852,"ele":328.8},
{"num":27.896,"ele":333.2},
{"num":27.949,"ele":335.3},
{"num":28.033,"ele":334.9},
{"num":28.159,"ele":336.2},
{"num":28.223,"ele":341.0},
{"num":28.279,"ele":344.1},
{"num":28.337,"ele":345.8},
{"num":28.403,"ele":350.2},
{"num":28.458,"ele":356.8},
{"num":28.491,"ele":361.3},
{"num":28.532,"ele":363.7},
{"num":28.574,"ele":368.2},
{"num":28.617,"ele":375.0},
{"num":28.662,"ele":380.0},
{"num":28.708,"ele":383.5},
{"num":28.754,"ele":384.9},
{"num":28.797,"ele":389.5},
{"num":28.844,"ele":394.1},
{"num":28.896,"ele":396.0},
{"num":28.946,"ele":399.1},
{"num":28.998,"ele":405.1},
{"num":29.050,"ele":410.6},
{"num":29.108,"ele":413.1},
{"num":29.162,"ele":416.6},
{"num":29.210,"ele":421.3},
{"num":29.263,"ele":425.0},
{"num":29.314,"ele":429.1},
{"num":29.364,"ele":433.3},
{"num":29.419,"ele":438.5},
{"num":29.465,"ele":441.2},
{"num":29.507,"ele":446.2},
{"num":29.556,"ele":448.9},
{"num":29.619,"ele":453.0},
{"num":29.687,"ele":453.9},
{"num":29.760,"ele":455.8},
{"num":29.872,"ele":457.7},
{"num":29.960,"ele":457.0},
{"num":30.075,"ele":456.1},
{"num":30.213,"ele":451.3},
{"num":30.348,"ele":449.9},
{"num":30.438,"ele":453.2},
{"num":30.503,"ele":457.1},
{"num":30.559,"ele":460.3},
{"num":30.616,"ele":463.8},
{"num":30.672,"ele":465.1},
{"num":30.771,"ele":463.6},
{"num":30.861,"ele":465.9},
{"num":30.920,"ele":469.8},
{"num":30.984,"ele":472.6},
{"num":31.095,"ele":470.8},
{"num":31.180,"ele":471.1},
{"num":31.270,"ele":471.0},
{"num":31.399,"ele":468.1},
{"num":31.502,"ele":473.3},
{"num":31.557,"ele":478.5},
{"num":31.610,"ele":481.9},
{"num":31.718,"ele":476.2},
{"num":31.831,"ele":470.7}
]